parallel_parrot/__init__.py
parallel_parrot/core.py
parallel_parrot/format_openai_fine_tuning.py
parallel_parrot/openai_api.py
parallel_parrot/openai_api_lib.py
parallel_parrot/openai_data_interface.py
parallel_parrot/openai_util.py
parallel_parrot/prompt_templates.py
parallel_parrot/py.typed
parallel_parrot/types.py
parallel_parrot/util.py
parallel_parrot/util_dictlist.py
parallel_parrot/util_pandas.py
parallel_parrot/util_template.py
parallel_parrot-0.9.0.dist-info/LICENSE
parallel_parrot-0.9.0.dist-info/METADATA
parallel_parrot-0.9.0.dist-info/WHEEL
parallel_parrot-0.9.0.dist-info/RECORD
