Metadata-Version: 2.1
Name: parallel-parrot
Version: 0.9.0
Summary: A library for easily and quickly using LLMs on tabular data
Home-page: https://github.com/novex-ai/parallel-parrot
License: MIT
Keywords: generative ai,pandas,llm,parallel,openai
Author: Brad Ito
Author-email: phlogisticfugu@gmail.com
Requires-Python: >=3.9,<3.12
Classifier: License :: OSI Approved :: MIT License
Classifier: Programming Language :: Python :: 3
Classifier: Programming Language :: Python :: 3.9
Classifier: Programming Language :: Python :: 3.10
Classifier: Programming Language :: Python :: 3.11
Provides-Extra: pandas
Requires-Dist: aiohttp (>=3.8.6,<4.0.0)
Requires-Dist: aiohttp-retry (>=2.8.3,<3.0.0)
Requires-Dist: asyncio-anywhere (>=0.2.0,<0.3.0)
Requires-Dist: dataclass-utils (>=0.7.23,<0.8.0)
Requires-Dist: pandas (>=1.0,<3.0) ; extra == "pandas"
Requires-Dist: tiktoken (>=0.5.1,<0.6.0)
Project-URL: Changelog, https://github.com/novex-ai/parallel-parrot/releases
Project-URL: Issues, https://github.com/novex-ai/parallel-parrot/issues
Project-URL: Repository, https://github.com/novex-ai/parallel-parrot
